{"config":{"output_file":null,"full_docs":false,"pub_only":true,"reachable_only":true,"distro_crate":false,"signatures":false,"borrow_data":false},"version":"0.18.0","prelude":{"crate_id":{"name":"tokio_signal","disambiguator":[14842506496524174880,7412686867226749375]},"crate_root":"/home/eric/.cargo/registry/src/github.com-1ecc6299db9ec823/tokio-signal-0.2.6/src","external_crates":[{"file_name":"/home/eric/.cargo/registry/src/github.com-1ecc6299db9ec823/tokio-signal-0.2.6/src/lib.rs","num":1,"id":{"name":"std","disambiguator":[7046065364473614619,10056788711089334333]}},{"file_name":"/home/eric/.cargo/registry/src/github.com-1ecc6299db9ec823/tokio-signal-0.2.6/src/lib.rs","num":2,"id":{"name":"core","disambiguator":[18045606665974499287,7370096489839769307]}},{"file_name":"/home/eric/.cargo/registry/src/github.com-1ecc6299db9ec823/tokio-signal-0.2.6/src/lib.rs","num":3,"id":{"name":"compiler_builtins","disambiguator":[8940449385909834963,3306656639318091857]}},{"file_name":"/home/eric/.cargo/registry/src/github.com-1ecc6299db9ec823/tokio-signal-0.2.6/src/lib.rs","num":4,"id":{"name":"alloc","disambiguator":[4650751871500514687,4336247883493526277]}},{"file_name":"/home/eric/.cargo/registry/src/github.com-1ecc6299db9ec823/tokio-signal-0.2.6/src/lib.rs","num":5,"id":{"name":"alloc_system","disambiguator":[2671025247590627007,221811983110420441]}},{"file_name":"/home/eric/.cargo/registry/src/github.com-1ecc6299db9ec823/tokio-signal-0.2.6/src/lib.rs","num":6,"id":{"name":"libc","disambiguator":[8453567920792120947,9168909440481815743]}},{"file_name":"/home/eric/.cargo/registry/src/github.com-1ecc6299db9ec823/tokio-signal-0.2.6/src/lib.rs","num":7,"id":{"name":"unwind","disambiguator":[18179531398593787271,9907519451984815572]}},{"file_name":"/home/eric/.cargo/registry/src/github.com-1ecc6299db9ec823/tokio-signal-0.2.6/src/lib.rs","num":8,"id":{"name":"alloc_jemalloc","disambiguator":[14986725973947038648,14534646976018034053]}},{"file_name":"/home/eric/.cargo/registry/src/github.com-1ecc6299db9ec823/tokio-signal-0.2.6/src/lib.rs","num":9,"id":{"name":"panic_unwind","disambiguator":[724428356685261056,12774823514128739995]}},{"file_name":"/home/eric/.cargo/registry/src/github.com-1ecc6299db9ec823/tokio-signal-0.2.6/src/lib.rs","num":10,"id":{"name":"futures","disambiguator":[11744181824296654106,5606580142342587701]}},{"file_name":"/home/eric/.cargo/registry/src/github.com-1ecc6299db9ec823/tokio-signal-0.2.6/src/lib.rs","num":11,"id":{"name":"mio","disambiguator":[1070479013138068819,4351486901890294586]}},{"file_name":"/home/eric/.cargo/registry/src/github.com-1ecc6299db9ec823/tokio-signal-0.2.6/src/lib.rs","num":12,"id":{"name":"lazycell","disambiguator":[3091467487478581615,6832333361435073983]}},{"file_name":"/home/eric/.cargo/registry/src/github.com-1ecc6299db9ec823/tokio-signal-0.2.6/src/lib.rs","num":13,"id":{"name":"net2","disambiguator":[12948169797699663524,8860465254415259478]}},{"file_name":"/home/eric/.cargo/registry/src/github.com-1ecc6299db9ec823/tokio-signal-0.2.6/src/unix.rs","num":14,"id":{"name":"libc","disambiguator":[16959940114727513389,4435599347966142126]}},{"file_name":"/home/eric/.cargo/registry/src/github.com-1ecc6299db9ec823/tokio-signal-0.2.6/src/lib.rs","num":15,"id":{"name":"cfg_if","disambiguator":[11427383368964817088,8544089969577660689]}},{"file_name":"/home/eric/.cargo/registry/src/github.com-1ecc6299db9ec823/tokio-signal-0.2.6/src/lib.rs","num":16,"id":{"name":"iovec","disambiguator":[13397234978404998743,17176089621322480917]}},{"file_name":"/home/eric/.cargo/registry/src/github.com-1ecc6299db9ec823/tokio-signal-0.2.6/src/lib.rs","num":17,"id":{"name":"slab","disambiguator":[16937934715566909778,8495862664286992642]}},{"file_name":"/home/eric/.cargo/registry/src/github.com-1ecc6299db9ec823/tokio-signal-0.2.6/src/lib.rs","num":18,"id":{"name":"log","disambiguator":[4941678426572324267,11894599032701238051]}},{"file_name":"/home/eric/.cargo/registry/src/github.com-1ecc6299db9ec823/tokio-signal-0.2.6/src/lib.rs","num":19,"id":{"name":"tokio_executor","disambiguator":[1279663579430728395,12260769835431499293]}},{"file_name":"/home/eric/.cargo/registry/src/github.com-1ecc6299db9ec823/tokio-signal-0.2.6/src/lib.rs","num":20,"id":{"name":"tokio_io","disambiguator":[17423549467535946385,3612366547950601059]}},{"file_name":"/home/eric/.cargo/registry/src/github.com-1ecc6299db9ec823/tokio-signal-0.2.6/src/lib.rs","num":21,"id":{"name":"bytes","disambiguator":[4539697919000604919,1174859332411669994]}},{"file_name":"/home/eric/.cargo/registry/src/github.com-1ecc6299db9ec823/tokio-signal-0.2.6/src/lib.rs","num":22,"id":{"name":"byteorder","disambiguator":[4390361276855900838,5777695070144406391]}},{"file_name":"/home/eric/.cargo/registry/src/github.com-1ecc6299db9ec823/tokio-signal-0.2.6/src/lib.rs","num":23,"id":{"name":"tokio_reactor","disambiguator":[832113729488630514,7460967013892404499]}},{"file_name":"/home/eric/.cargo/registry/src/github.com-1ecc6299db9ec823/tokio-signal-0.2.6/src/lib.rs","num":24,"id":{"name":"crossbeam_utils","disambiguator":[18069234646856882546,5989421414976270063]}},{"file_name":"/home/eric/.cargo/registry/src/github.com-1ecc6299db9ec823/tokio-signal-0.2.6/src/lib.rs","num":25,"id":{"name":"lazy_static","disambiguator":[17326296804847731044,18381035407715517402]}},{"file_name":"/home/eric/.cargo/registry/src/github.com-1ecc6299db9ec823/tokio-signal-0.2.6/src/lib.rs","num":26,"id":{"name":"num_cpus","disambiguator":[14432951741442061616,3786343405955684404]}},{"file_name":"/home/eric/.cargo/registry/src/github.com-1ecc6299db9ec823/tokio-signal-0.2.6/src/lib.rs","num":27,"id":{"name":"parking_lot","disambiguator":[7427873074551326769,12482145710653307281]}},{"file_name":"/home/eric/.cargo/registry/src/github.com-1ecc6299db9ec823/tokio-signal-0.2.6/src/lib.rs","num":28,"id":{"name":"lock_api","disambiguator":[12469733717151218939,13378655526358242465]}},{"file_name":"/home/eric/.cargo/registry/src/github.com-1ecc6299db9ec823/tokio-signal-0.2.6/src/lib.rs","num":29,"id":{"name":"scopeguard","disambiguator":[12828865114892905142,17234398841200553742]}},{"file_name":"/home/eric/.cargo/registry/src/github.com-1ecc6299db9ec823/tokio-signal-0.2.6/src/lib.rs","num":30,"id":{"name":"owning_ref","disambiguator":[8423271353957782291,8068354304360970526]}},{"file_name":"/home/eric/.cargo/registry/src/github.com-1ecc6299db9ec823/tokio-signal-0.2.6/src/lib.rs","num":31,"id":{"name":"stable_deref_trait","disambiguator":[10710178353765643070,13640834741843657275]}},{"file_name":"/home/eric/.cargo/registry/src/github.com-1ecc6299db9ec823/tokio-signal-0.2.6/src/lib.rs","num":32,"id":{"name":"parking_lot_core","disambiguator":[13932432165274259497,6656147165152441]}},{"file_name":"/home/eric/.cargo/registry/src/github.com-1ecc6299db9ec823/tokio-signal-0.2.6/src/lib.rs","num":33,"id":{"name":"rand","disambiguator":[9598935148827111951,14506664467398620940]}},{"file_name":"/home/eric/.cargo/registry/src/github.com-1ecc6299db9ec823/tokio-signal-0.2.6/src/lib.rs","num":34,"id":{"name":"rand_core","disambiguator":[1044703304555423375,8781605820769296829]}},{"file_name":"/home/eric/.cargo/registry/src/github.com-1ecc6299db9ec823/tokio-signal-0.2.6/src/lib.rs","num":35,"id":{"name":"rand_core","disambiguator":[13758289448472234922,9458539481446455988]}},{"file_name":"/home/eric/.cargo/registry/src/github.com-1ecc6299db9ec823/tokio-signal-0.2.6/src/lib.rs","num":36,"id":{"name":"smallvec","disambiguator":[4536756746623320837,10573657633560644418]}},{"file_name":"/home/eric/.cargo/registry/src/github.com-1ecc6299db9ec823/tokio-signal-0.2.6/src/lib.rs","num":37,"id":{"name":"unreachable","disambiguator":[8934767556264436149,11436399862582082574]}},{"file_name":"/home/eric/.cargo/registry/src/github.com-1ecc6299db9ec823/tokio-signal-0.2.6/src/lib.rs","num":38,"id":{"name":"void","disambiguator":[12977147536065816480,14778814323986605803]}},{"file_name":"/home/eric/.cargo/registry/src/github.com-1ecc6299db9ec823/tokio-signal-0.2.6/src/unix.rs","num":39,"id":{"name":"mio_uds","disambiguator":[252281733602843648,11778912621576070835]}},{"file_name":"/home/eric/.cargo/registry/src/github.com-1ecc6299db9ec823/tokio-signal-0.2.6/src/unix.rs","num":40,"id":{"name":"signal_hook","disambiguator":[14457200393114220391,13484552672185978390]}},{"file_name":"/home/eric/.cargo/registry/src/github.com-1ecc6299db9ec823/tokio-signal-0.2.6/src/unix.rs","num":41,"id":{"name":"arc_swap","disambiguator":[17033724031270765941,17240677928124891397]}}],"span":{"file_name":[47,104,111,109,101,47,101,114,105,99,47,46,99,97,114,103,111,47,114,101,103,105,115,116,114,121,47,115,114,99,47,103,105,116,104,117,98,46,99,111,109,45,49,101,99,99,54,50,57,57,100,98,57,101,99,56,50,51,47,116,111,107,105,111,45,115,105,103,110,97,108,45,48,46,50,46,54,47,115,114,99,47,108,105,98,46,114,115],"byte_start":0,"byte_end":4874,"line_start":1,"line_end":141,"column_start":1,"column_end":2}},"imports":[{"kind":"Use","ref_id":{"krate":14,"index":5636},"span":{"file_name":[47,104,111,109,101,47,101,114,105,99,47,46,99,97,114,103,111,47,114,101,103,105,115,116,114,121,47,115,114,99,47,103,105,116,104,117,98,46,99,111,109,45,49,101,99,99,54,50,57,57,100,98,57,101,99,56,50,51,47,116,111,107,105,111,45,115,105,103,110,97,108,45,48,46,50,46,54,47,115,114,99,47,117,110,105,120,46,114,115],"byte_start":5610,"byte_end":5617,"line_start":27,"line_end":27,"column_start":22,"column_end":29},"alias_span":null,"name":"SIGUSR1","value":"","parent":{"krate":0,"index":28}},{"kind":"Use","ref_id":{"krate":14,"index":5638},"span":{"file_name":[47,104,111,109,101,47,101,114,105,99,47,46,99,97,114,103,111,47,114,101,103,105,115,116,114,121,47,115,114,99,47,103,105,116,104,117,98,46,99,111,109,45,49,101,99,99,54,50,57,57,100,98,57,101,99,56,50,51,47,116,111,107,105,111,45,115,105,103,110,97,108,45,48,46,50,46,54,47,115,114,99,47,117,110,105,120,46,114,115],"byte_start":5619,"byte_end":5626,"line_start":27,"line_end":27,"column_start":31,"column_end":38},"alias_span":null,"name":"SIGUSR2","value":"","parent":{"krate":0,"index":28}},{"kind":"Use","ref_id":{"krate":14,"index":624},"span":{"file_name":[47,104,111,109,101,47,101,114,105,99,47,46,99,97,114,103,111,47,114,101,103,105,115,116,114,121,47,115,114,99,47,103,105,116,104,117,98,46,99,111,109,45,49,101,99,99,54,50,57,57,100,98,57,101,99,56,50,51,47,116,111,107,105,111,45,115,105,103,110,97,108,45,48,46,50,46,54,47,115,114,99,47,117,110,105,120,46,114,115],"byte_start":5628,"byte_end":5634,"line_start":27,"line_end":27,"column_start":40,"column_end":46},"alias_span":null,"name":"SIGINT","value":"","parent":{"krate":0,"index":28}},{"kind":"Use","ref_id":{"krate":14,"index":642},"span":{"file_name":[47,104,111,109,101,47,101,114,105,99,47,46,99,97,114,103,111,47,114,101,103,105,115,116,114,121,47,115,114,99,47,103,105,116,104,117,98,46,99,111,109,45,49,101,99,99,54,50,57,57,100,98,57,101,99,56,50,51,47,116,111,107,105,111,45,115,105,103,110,97,108,45,48,46,50,46,54,47,115,114,99,47,117,110,105,120,46,114,115],"byte_start":5636,"byte_end":5643,"line_start":27,"line_end":27,"column_start":48,"column_end":55},"alias_span":null,"name":"SIGTERM","value":"","parent":{"krate":0,"index":28}},{"kind":"Use","ref_id":{"krate":14,"index":640},"span":{"file_name":[47,104,111,109,101,47,101,114,105,99,47,46,99,97,114,103,111,47,114,101,103,105,115,116,114,121,47,115,114,99,47,103,105,116,104,117,98,46,99,111,109,45,49,101,99,99,54,50,57,57,100,98,57,101,99,56,50,51,47,116,111,107,105,111,45,115,105,103,110,97,108,45,48,46,50,46,54,47,115,114,99,47,117,110,105,120,46,114,115],"byte_start":5667,"byte_end":5674,"line_start":28,"line_end":28,"column_start":22,"column_end":29},"alias_span":null,"name":"SIGALRM","value":"","parent":{"krate":0,"index":28}},{"kind":"Use","ref_id":{"krate":14,"index":622},"span":{"file_name":[47,104,111,109,101,47,101,114,105,99,47,46,99,97,114,103,111,47,114,101,103,105,115,116,114,121,47,115,114,99,47,103,105,116,104,117,98,46,99,111,109,45,49,101,99,99,54,50,57,57,100,98,57,101,99,56,50,51,47,116,111,107,105,111,45,115,105,103,110,97,108,45,48,46,50,46,54,47,115,114,99,47,117,110,105,120,46,114,115],"byte_start":5676,"byte_end":5682,"line_start":28,"line_end":28,"column_start":31,"column_end":37},"alias_span":null,"name":"SIGHUP","value":"","parent":{"krate":0,"index":28}},{"kind":"Use","ref_id":{"krate":14,"index":638},"span":{"file_name":[47,104,111,109,101,47,101,114,105,99,47,46,99,97,114,103,111,47,114,101,103,105,115,116,114,121,47,115,114,99,47,103,105,116,104,117,98,46,99,111,109,45,49,101,99,99,54,50,57,57,100,98,57,101,99,56,50,51,47,116,111,107,105,111,45,115,105,103,110,97,108,45,48,46,50,46,54,47,115,114,99,47,117,110,105,120,46,114,115],"byte_start":5684,"byte_end":5691,"line_start":28,"line_end":28,"column_start":39,"column_end":46},"alias_span":null,"name":"SIGPIPE","value":"","parent":{"krate":0,"index":28}},{"kind":"Use","ref_id":{"krate":14,"index":626},"span":{"file_name":[47,104,111,109,101,47,101,114,105,99,47,46,99,97,114,103,111,47,114,101,103,105,115,116,114,121,47,115,114,99,47,103,105,116,104,117,98,46,99,111,109,45,49,101,99,99,54,50,57,57,100,98,57,101,99,56,50,51,47,116,111,107,105,111,45,115,105,103,110,97,108,45,48,46,50,46,54,47,115,114,99,47,117,110,105,120,46,114,115],"byte_start":5693,"byte_end":5700,"line_start":28,"line_end":28,"column_start":48,"column_end":55},"alias_span":null,"name":"SIGQUIT","value":"","parent":{"krate":0,"index":28}},{"kind":"Use","ref_id":{"krate":14,"index":510},"span":{"file_name":[47,104,111,109,101,47,101,114,105,99,47,46,99,97,114,103,111,47,114,101,103,105,115,116,114,121,47,115,114,99,47,103,105,116,104,117,98,46,99,111,109,45,49,101,99,99,54,50,57,57,100,98,57,101,99,56,50,51,47,116,111,107,105,111,45,115,105,103,110,97,108,45,48,46,50,46,54,47,115,114,99,47,117,110,105,120,46,114,115],"byte_start":5702,"byte_end":5709,"line_start":28,"line_end":28,"column_start":57,"column_end":64},"alias_span":null,"name":"SIGTRAP","value":"","parent":{"krate":0,"index":28}}],"defs":[{"kind":"Mod","id":{"krate":0,"index":0},"span":{"file_name":[47,104,111,109,101,47,101,114,105,99,47,46,99,97,114,103,111,47,114,101,103,105,115,116,114,121,47,115,114,99,47,103,105,116,104,117,98,46,99,111,109,45,49,101,99,99,54,50,57,57,100,98,57,101,99,56,50,51,47,116,111,107,105,111,45,115,105,103,110,97,108,45,48,46,50,46,54,47,115,114,99,47,108,105,98,46,114,115],"byte_start":0,"byte_end":4874,"line_start":1,"line_end":141,"column_start":1,"column_end":2},"name":"","qualname":"::","value":"/home/eric/.cargo/registry/src/github.com-1ecc6299db9ec823/tokio-signal-0.2.6/src/lib.rs","parent":null,"children":[{"krate":0,"index":2},{"krate":0,"index":4},{"krate":0,"index":6},{"krate":0,"index":8},{"krate":0,"index":10},{"krate":0,"index":12},{"krate":0,"index":14},{"krate":0,"index":16},{"krate":0,"index":18},{"krate":0,"index":20},{"krate":0,"index":26},{"krate":0,"index":28},{"krate":0,"index":182},{"krate":0,"index":184},{"krate":0,"index":186},{"krate":0,"index":188}],"decl_id":null,"docs":" Asynchronous signal handling for Tokio","sig":null,"attributes":[{"value":"deny(missing_docs)","span":{"file_name":[47,104,111,109,101,47,101,114,105,99,47,46,99,97,114,103,111,47,114,101,103,105,115,116,114,121,47,115,114,99,47,103,105,116,104,117,98,46,99,111,109,45,49,101,99,99,54,50,57,57,100,98,57,101,99,56,50,51,47,116,111,107,105,111,45,115,105,103,110,97,108,45,48,46,50,46,54,47,115,114,99,47,108,105,98,46,114,115],"byte_start":2237,"byte_end":2259,"line_start":71,"line_end":71,"column_start":1,"column_end":23}}]},{"kind":"Mod","id":{"krate":0,"index":28},"span":{"file_name":[47,104,111,109,101,47,101,114,105,99,47,46,99,97,114,103,111,47,114,101,103,105,115,116,114,121,47,115,114,99,47,103,105,116,104,117,98,46,99,111,109,45,49,101,99,99,54,50,57,57,100,98,57,101,99,56,50,51,47,116,111,107,105,111,45,115,105,103,110,97,108,45,48,46,50,46,54,47,115,114,99,47,117,110,105,120,46,114,115],"byte_start":0,"byte_end":0,"line_start":1,"line_end":1,"column_start":1,"column_end":1},"name":"unix","qualname":"::unix","value":"/home/eric/.cargo/registry/src/github.com-1ecc6299db9ec823/tokio-signal-0.2.6/src/unix.rs","parent":null,"children":[{"krate":0,"index":30},{"krate":0,"index":32},{"krate":0,"index":34},{"krate":0,"index":36},{"krate":0,"index":38},{"krate":0,"index":46},{"krate":0,"index":48},{"krate":0,"index":54},{"krate":0,"index":62},{"krate":0,"index":64},{"krate":0,"index":66},{"krate":0,"index":68},{"krate":0,"index":76},{"krate":0,"index":84},{"krate":0,"index":92},{"krate":0,"index":98},{"krate":0,"index":100},{"krate":0,"index":110},{"krate":0,"index":122},{"krate":0,"index":124},{"krate":0,"index":126},{"krate":0,"index":128},{"krate":0,"index":132},{"krate":0,"index":134},{"krate":0,"index":138},{"krate":0,"index":140},{"krate":0,"index":142},{"krate":0,"index":144},{"krate":0,"index":152},{"krate":0,"index":160},{"krate":0,"index":162},{"krate":0,"index":164},{"krate":0,"index":170},{"krate":0,"index":178}],"decl_id":null,"docs":" Unix-specific types for signal handling.","sig":null,"attributes":[{"value":"cfg(unix)","span":{"file_name":[47,104,111,109,101,47,101,114,105,99,47,46,99,97,114,103,111,47,114,101,103,105,115,116,114,121,47,115,114,99,47,103,105,116,104,117,98,46,99,111,109,45,49,101,99,99,54,50,57,57,100,98,57,101,99,56,50,51,47,116,111,107,105,111,45,115,105,103,110,97,108,45,48,46,50,46,54,47,115,114,99,47,117,110,105,120,46,114,115],"byte_start":5059,"byte_end":5072,"line_start":6,"line_end":6,"column_start":1,"column_end":14}}]},{"kind":"Struct","id":{"krate":0,"index":160},"span":{"file_name":[47,104,111,109,101,47,101,114,105,99,47,46,99,97,114,103,111,47,114,101,103,105,115,116,114,121,47,115,114,99,47,103,105,116,104,117,98,46,99,111,109,45,49,101,99,99,54,50,57,57,100,98,57,101,99,56,50,51,47,116,111,107,105,111,45,115,105,103,110,97,108,45,48,46,50,46,54,47,115,114,99,47,117,110,105,120,46,114,115],"byte_start":14975,"byte_end":14981,"line_start":274,"line_end":274,"column_start":12,"column_end":18},"name":"Signal","qualname":"::unix::Signal","value":"Signal {  }","parent":null,"children":[{"krate":0,"index":47},{"krate":0,"index":49},{"krate":0,"index":51},{"krate":0,"index":53}],"decl_id":null,"docs":" An implementation of `Stream` for receiving a particular type of signal.","sig":null,"attributes":[]},{"kind":"Method","id":{"krate":0,"index":166},"span":{"file_name":[47,104,111,109,101,47,101,114,105,99,47,46,99,97,114,103,111,47,114,101,103,105,115,116,114,121,47,115,114,99,47,103,105,116,104,117,98,46,99,111,109,45,49,101,99,99,54,50,57,57,100,98,57,101,99,56,50,51,47,116,111,107,105,111,45,115,105,103,110,97,108,45,48,46,50,46,54,47,115,114,99,47,117,110,105,120,46,114,115],"byte_start":16868,"byte_end":16871,"line_start":316,"line_end":316,"column_start":12,"column_end":15},"name":"new","qualname":"<Signal>::new","value":"fn (signal: c_int) -> IoFuture<Signal>","parent":null,"children":[],"decl_id":null,"docs":" Creates a new stream which will receive notifications when the current\n process receives the signal `signal`.","sig":null,"attributes":[]},{"kind":"Method","id":{"krate":0,"index":168},"span":{"file_name":[47,104,111,109,101,47,101,114,105,99,47,46,99,97,114,103,111,47,114,101,103,105,115,116,114,121,47,115,114,99,47,103,105,116,104,117,98,46,99,111,109,45,49,101,99,99,54,50,57,57,100,98,57,101,99,56,50,51,47,116,111,107,105,111,45,115,105,103,110,97,108,45,48,46,50,46,54,47,115,114,99,47,117,110,105,120,46,114,115],"byte_start":17953,"byte_end":17964,"line_start":338,"line_end":338,"column_start":12,"column_end":23},"name":"with_handle","qualname":"<Signal>::with_handle","value":"fn (signal: c_int, handle: &Handle) -> IoFuture<Signal>","parent":null,"children":[],"decl_id":null,"docs":" Creates a new stream which will receive notifications when the current\n process receives the signal `signal`.","sig":null,"attributes":[]},{"kind":"Type","id":{"krate":0,"index":182},"span":{"file_name":[47,104,111,109,101,47,101,114,105,99,47,46,99,97,114,103,111,47,114,101,103,105,115,116,114,121,47,115,114,99,47,103,105,116,104,117,98,46,99,111,109,45,49,101,99,99,54,50,57,57,100,98,57,101,99,56,50,51,47,116,111,107,105,111,45,115,105,103,110,97,108,45,48,46,50,46,54,47,115,114,99,47,108,105,98,46,114,115],"byte_start":2565,"byte_end":2573,"line_start":89,"line_end":89,"column_start":10,"column_end":18},"name":"IoFuture","qualname":"::IoFuture","value":"Box<Future<Item = T, Error = io::Error> + Send>","parent":null,"children":[],"decl_id":null,"docs":" A future whose error is `io::Error`\n","sig":null,"attributes":[]},{"kind":"Type","id":{"krate":0,"index":184},"span":{"file_name":[47,104,111,109,101,47,101,114,105,99,47,46,99,97,114,103,111,47,114,101,103,105,115,116,114,121,47,115,114,99,47,103,105,116,104,117,98,46,99,111,109,45,49,101,99,99,54,50,57,57,100,98,57,101,99,56,50,51,47,116,111,107,105,111,45,115,105,103,110,97,108,45,48,46,50,46,54,47,115,114,99,47,108,105,98,46,114,115],"byte_start":2677,"byte_end":2685,"line_start":91,"line_end":91,"column_start":10,"column_end":18},"name":"IoStream","qualname":"::IoStream","value":"Box<Stream<Item = T, Error = io::Error> + Send>","parent":null,"children":[],"decl_id":null,"docs":" A stream whose error is `io::Error`\n","sig":null,"attributes":[]},{"kind":"Function","id":{"krate":0,"index":186},"span":{"file_name":[47,104,111,109,101,47,101,114,105,99,47,46,99,97,114,103,111,47,114,101,103,105,115,116,114,121,47,115,114,99,47,103,105,116,104,117,98,46,99,111,109,45,49,101,99,99,54,50,57,57,100,98,57,101,99,56,50,51,47,116,111,107,105,111,45,115,105,103,110,97,108,45,48,46,50,46,54,47,115,114,99,47,108,105,98,46,114,115],"byte_start":3313,"byte_end":3319,"line_start":104,"line_end":104,"column_start":8,"column_end":14},"name":"ctrl_c","qualname":"::ctrl_c","value":"fn () -> IoFuture<IoStream<()>>","parent":null,"children":[],"decl_id":null,"docs":" Creates a stream which receives \"ctrl-c\" notifications sent to a process.","sig":null,"attributes":[]},{"kind":"Function","id":{"krate":0,"index":188},"span":{"file_name":[47,104,111,109,101,47,101,114,105,99,47,46,99,97,114,103,111,47,114,101,103,105,115,116,114,121,47,115,114,99,47,103,105,116,104,117,98,46,99,111,109,45,49,101,99,99,54,50,57,57,100,98,57,101,99,56,50,51,47,116,111,107,105,111,45,115,105,103,110,97,108,45,48,46,50,46,54,47,115,114,99,47,108,105,98,46,114,115],"byte_start":4057,"byte_end":4070,"line_start":120,"line_end":120,"column_start":8,"column_end":21},"name":"ctrl_c_handle","qualname":"::ctrl_c_handle","value":"fn (handle: &Handle) -> IoFuture<IoStream<()>>","parent":null,"children":[],"decl_id":null,"docs":" Creates a stream which receives \"ctrl-c\" notifications sent to a process.","sig":null,"attributes":[]}],"impls":[{"id":0,"kind":"Direct","span":{"file_name":[47,104,111,109,101,47,101,114,105,99,47,46,99,97,114,103,111,47,114,101,103,105,115,116,114,121,47,115,114,99,47,103,105,116,104,117,98,46,99,111,109,45,49,101,99,99,54,50,57,57,100,98,57,101,99,56,50,51,47,116,111,107,105,111,45,115,105,103,110,97,108,45,48,46,50,46,54,47,115,114,99,47,117,110,105,120,46,114,115],"byte_start":6504,"byte_end":6514,"line_start":64,"line_end":64,"column_start":18,"column_end":28},"value":"","parent":null,"children":[{"krate":0,"index":130}],"docs":"","sig":null,"attributes":[]},{"id":1,"kind":"Direct","span":{"file_name":[47,104,111,109,101,47,101,114,105,99,47,46,99,97,114,103,111,47,114,101,103,105,115,116,114,121,47,115,114,99,47,103,105,116,104,117,98,46,99,111,109,45,49,101,99,99,54,50,57,57,100,98,57,101,99,56,50,51,47,116,111,107,105,111,45,115,105,103,110,97,108,45,48,46,50,46,54,47,115,114,99,47,117,110,105,120,46,114,115],"byte_start":9289,"byte_end":9295,"line_start":148,"line_end":148,"column_start":17,"column_end":23},"value":"","parent":null,"children":[{"krate":0,"index":146},{"krate":0,"index":148},{"krate":0,"index":150}],"docs":"","sig":null,"attributes":[]},{"id":2,"kind":"Inherent","span":{"file_name":[47,104,111,109,101,47,101,114,105,99,47,46,99,97,114,103,111,47,114,101,103,105,115,116,114,121,47,115,114,99,47,103,105,116,104,117,98,46,99,111,109,45,49,101,99,99,54,50,57,57,100,98,57,101,99,56,50,51,47,116,111,107,105,111,45,115,105,103,110,97,108,45,48,46,50,46,54,47,115,114,99,47,117,110,105,120,46,114,115],"byte_start":9667,"byte_end":9673,"line_start":163,"line_end":163,"column_start":6,"column_end":12},"value":"","parent":null,"children":[{"krate":0,"index":154},{"krate":0,"index":156},{"krate":0,"index":158}],"docs":"","sig":null,"attributes":[]},{"id":3,"kind":"Direct","span":{"file_name":[47,104,111,109,101,47,101,114,105,99,47,46,99,97,114,103,111,47,114,101,103,105,115,116,114,121,47,115,114,99,47,103,105,116,104,117,98,46,99,111,109,45,49,101,99,99,54,50,57,57,100,98,57,101,99,56,50,51,47,116,111,107,105,111,45,115,105,103,110,97,108,45,48,46,50,46,54,47,115,114,99,47,117,110,105,120,46,114,115],"byte_start":15570,"byte_end":15576,"line_start":288,"line_end":288,"column_start":22,"column_end":28},"value":"","parent":null,"children":[],"docs":"","sig":null,"attributes":[]},{"id":4,"kind":"Inherent","span":{"file_name":[47,104,111,109,101,47,101,114,105,99,47,46,99,97,114,103,111,47,114,101,103,105,115,116,114,121,47,115,114,99,47,103,105,116,104,117,98,46,99,111,109,45,49,101,99,99,54,50,57,57,100,98,57,101,99,56,50,51,47,116,111,107,105,111,45,115,105,103,110,97,108,45,48,46,50,46,54,47,115,114,99,47,117,110,105,120,46,114,115],"byte_start":15586,"byte_end":15592,"line_start":290,"line_end":290,"column_start":6,"column_end":12},"value":"","parent":null,"children":[{"krate":0,"index":166},{"krate":0,"index":168}],"docs":"","sig":null,"attributes":[]},{"id":5,"kind":"Direct","span":{"file_name":[47,104,111,109,101,47,101,114,105,99,47,46,99,97,114,103,111,47,114,101,103,105,115,116,114,121,47,115,114,99,47,103,105,116,104,117,98,46,99,111,109,45,49,101,99,99,54,50,57,57,100,98,57,101,99,56,50,51,47,116,111,107,105,111,45,115,105,103,110,97,108,45,48,46,50,46,54,47,115,114,99,47,117,110,105,120,46,114,115],"byte_start":19031,"byte_end":19037,"line_start":368,"line_end":368,"column_start":17,"column_end":23},"value":"","parent":null,"children":[{"krate":0,"index":172},{"krate":0,"index":174},{"krate":0,"index":176}],"docs":"","sig":null,"attributes":[]},{"id":6,"kind":"Direct","span":{"file_name":[47,104,111,109,101,47,101,114,105,99,47,46,99,97,114,103,111,47,114,101,103,105,115,116,114,121,47,115,114,99,47,103,105,116,104,117,98,46,99,111,109,45,49,101,99,99,54,50,57,57,100,98,57,101,99,56,50,51,47,116,111,107,105,111,45,115,105,103,110,97,108,45,48,46,50,46,54,47,115,114,99,47,117,110,105,120,46,114,115],"byte_start":19299,"byte_end":19305,"line_start":379,"line_end":379,"column_start":15,"column_end":21},"value":"","parent":null,"children":[{"krate":0,"index":180}],"docs":"","sig":null,"attributes":[]}],"refs":[{"kind":"Mod","span":{"file_name":[47,104,111,109,101,47,101,114,105,99,47,46,99,97,114,103,111,47,114,101,103,105,115,116,114,121,47,115,114,99,47,103,105,116,104,117,98,46,99,111,109,45,49,101,99,99,54,50,57,57,100,98,57,101,99,56,50,51,47,116,111,107,105,111,45,115,105,103,110,97,108,45,48,46,50,46,54,47,115,114,99,47,108,105,98,46,114,115],"byte_start":2492,"byte_end":2496,"line_start":85,"line_end":85,"column_start":9,"column_end":13},"ref_id":{"krate":0,"index":28}}],"macro_refs":[],"relations":[{"span":{"file_name":[47,104,111,109,101,47,101,114,105,99,47,46,99,97,114,103,111,47,114,101,103,105,115,116,114,121,47,115,114,99,47,103,105,116,104,117,98,46,99,111,109,45,49,101,99,99,54,50,57,57,100,98,57,101,99,56,50,51,47,116,111,107,105,111,45,115,105,103,110,97,108,45,48,46,50,46,54,47,115,114,99,47,117,110,105,120,46,114,115],"byte_start":6504,"byte_end":6514,"line_start":64,"line_end":64,"column_start":18,"column_end":28},"kind":{"variant":"Impl","fields":[0]},"from":{"krate":0,"index":124},"to":{"krate":2,"index":2540}},{"span":{"file_name":[47,104,111,109,101,47,101,114,105,99,47,46,99,97,114,103,111,47,114,101,103,105,115,116,114,121,47,115,114,99,47,103,105,116,104,117,98,46,99,111,109,45,49,101,99,99,54,50,57,57,100,98,57,101,99,56,50,51,47,116,111,107,105,111,45,115,105,103,110,97,108,45,48,46,50,46,54,47,115,114,99,47,117,110,105,120,46,114,115],"byte_start":9289,"byte_end":9295,"line_start":148,"line_end":148,"column_start":17,"column_end":23},"kind":{"variant":"Impl","fields":[1]},"from":{"krate":0,"index":142},"to":{"krate":10,"index":668}},{"span":{"file_name":[47,104,111,109,101,47,101,114,105,99,47,46,99,97,114,103,111,47,114,101,103,105,115,116,114,121,47,115,114,99,47,103,105,116,104,117,98,46,99,111,109,45,49,101,99,99,54,50,57,57,100,98,57,101,99,56,50,51,47,116,111,107,105,111,45,115,105,103,110,97,108,45,48,46,50,46,54,47,115,114,99,47,117,110,105,120,46,114,115],"byte_start":9667,"byte_end":9673,"line_start":163,"line_end":163,"column_start":6,"column_end":12},"kind":{"variant":"Impl","fields":[2]},"from":{"krate":0,"index":142},"to":{"krate":4294967295,"index":4294967295}},{"span":{"file_name":[47,104,111,109,101,47,101,114,105,99,47,46,99,97,114,103,111,47,114,101,103,105,115,116,114,121,47,115,114,99,47,103,105,116,104,117,98,46,99,111,109,45,49,101,99,99,54,50,57,57,100,98,57,101,99,56,50,51,47,116,111,107,105,111,45,115,105,103,110,97,108,45,48,46,50,46,54,47,115,114,99,47,117,110,105,120,46,114,115],"byte_start":15570,"byte_end":15576,"line_start":288,"line_end":288,"column_start":22,"column_end":28},"kind":{"variant":"Impl","fields":[3]},"from":{"krate":0,"index":160},"to":{"krate":2,"index":1638}},{"span":{"file_name":[47,104,111,109,101,47,101,114,105,99,47,46,99,97,114,103,111,47,114,101,103,105,115,116,114,121,47,115,114,99,47,103,105,116,104,117,98,46,99,111,109,45,49,101,99,99,54,50,57,57,100,98,57,101,99,56,50,51,47,116,111,107,105,111,45,115,105,103,110,97,108,45,48,46,50,46,54,47,115,114,99,47,117,110,105,120,46,114,115],"byte_start":15586,"byte_end":15592,"line_start":290,"line_end":290,"column_start":6,"column_end":12},"kind":{"variant":"Impl","fields":[4]},"from":{"krate":0,"index":160},"to":{"krate":4294967295,"index":4294967295}},{"span":{"file_name":[47,104,111,109,101,47,101,114,105,99,47,46,99,97,114,103,111,47,114,101,103,105,115,116,114,121,47,115,114,99,47,103,105,116,104,117,98,46,99,111,109,45,49,101,99,99,54,50,57,57,100,98,57,101,99,56,50,51,47,116,111,107,105,111,45,115,105,103,110,97,108,45,48,46,50,46,54,47,115,114,99,47,117,110,105,120,46,114,115],"byte_start":19031,"byte_end":19037,"line_start":368,"line_end":368,"column_start":17,"column_end":23},"kind":{"variant":"Impl","fields":[5]},"from":{"krate":0,"index":160},"to":{"krate":10,"index":2046}},{"span":{"file_name":[47,104,111,109,101,47,101,114,105,99,47,46,99,97,114,103,111,47,114,101,103,105,115,116,114,121,47,115,114,99,47,103,105,116,104,117,98,46,99,111,109,45,49,101,99,99,54,50,57,57,100,98,57,101,99,56,50,51,47,116,111,107,105,111,45,115,105,103,110,97,108,45,48,46,50,46,54,47,115,114,99,47,117,110,105,120,46,114,115],"byte_start":19299,"byte_end":19305,"line_start":379,"line_end":379,"column_start":15,"column_end":21},"kind":{"variant":"Impl","fields":[6]},"from":{"krate":0,"index":160},"to":{"krate":2,"index":1910}}]}